app/__init__.py
app/callbacks.py
app/dashboard.py
app/layout.py
app/assets/dark-theme.css
data/__init__.py
data/api_client.py
Platts_eWindow_dashboard-1.0.6.dist-info/LICENSE
Platts_eWindow_dashboard-1.0.6.dist-info/METADATA
Platts_eWindow_dashboard-1.0.6.dist-info/WHEEL
Platts_eWindow_dashboard-1.0.6.dist-info/entry_points.txt
Platts_eWindow_dashboard-1.0.6.dist-info/top_level.txt
Platts_eWindow_dashboard-1.0.6.dist-info/RECORD
