Metadata-Version: 2.1
Name: Platts-eWindow-dashboard
Version: 1.0.6
Summary: A Dash app for visualizing Platts eWindow data
Author: Magnum35puc
License-File: LICENSE
Requires-Dist: dash>=2.0.0
Requires-Dist: plotly>=5.0.0
Requires-Dist: pandas
Requires-Dist: requests
